starlette_bugsnag/__init__.py
starlette_bugsnag/middleware.py
starlette_bugsnag/types.py
starlette_bugsnag-0.2.1.data/data/LICENSE
tests/__init__.py
tests/test_bugsnag.py
starlette_bugsnag-0.2.1.dist-info/LICENSE
starlette_bugsnag-0.2.1.dist-info/METADATA
starlette_bugsnag-0.2.1.dist-info/WHEEL
starlette_bugsnag-0.2.1.dist-info/top_level.txt
starlette_bugsnag-0.2.1.dist-info/RECORD
