Metadata-Version: 2.1
Name: starlette-bugsnag
Version: 0.2.1
Summary: UNKNOWN
Home-page: https://github.com/ashinabraham/starlette-bugsnag
Author: Ashin E Abraham
Author-email: ashineabraham@gmail.com
License: MIT
Platform: UNKNOWN
Classifier: Natural Language :: English
Classifier: Development Status :: 5 - Production/Stable
Classifier: Environment :: Web Environment
Classifier: Operating System :: OS Independent
Classifier: Topic :: Internet :: WWW/HTTP
Classifier: License :: OSI Approved :: MIT License
Classifier: Programming Language :: Python :: 3
Classifier: Programming Language :: Python :: 3.6
Classifier: Programming Language :: Python :: 3.7
Requires-Python: >=3.6
Requires-Dist: bugsnag
Requires-Dist: starlette
